LICENSE.md
README.md
setup.py
kthreading/__init__.py
kthreading/classes.py
kthreading/exceptions.py
kthreading/functions.py
kthreading/kthread.py
kthreading/utils.py
kthreading.egg-info/PKG-INFO
kthreading.egg-info/SOURCES.txt
kthreading.egg-info/dependency_links.txt
kthreading.egg-info/top_level.txt