Metadata-Version: 2.1
Name: kthreading
Version: 0.3
Summary: Get more controls over threads
Classifier: Programming Language :: Python :: 3
Classifier: License :: OSI Approved :: MIT License
Requires-Python: >=3.5
License-File: LICENSE.md
